asynchelper/TaskExecutor.py
asynchelper/__init__.py
asynchelper-0.1.4.dist-info/LICENSE
asynchelper-0.1.4.dist-info/WHEEL
asynchelper-0.1.4.dist-info/METADATA
asynchelper-0.1.4.dist-info/RECORD
