Metadata-Version: 2.1
Name: asynchelper
Version: 0.1.4
Summary: asynchelper - Allows execution of unlimited number of asynchronous tasks while limiting the amount of active concurrent ones.
Home-page: https://github.com/darkarp/asynchelper
Author: Mario Nascimento
Author-email: mario@whitehathacking.tech
Requires-Python: >=3.7
Classifier: License :: OSI Approved :: MIT License
